hdx/freshness/__init__.py
hdx/freshness/_version.py
hdx/freshness/app/__init__.py
hdx/freshness/app/__main__.py
hdx/freshness/app/datafreshness.py
hdx/freshness/app/project_configuration.yml
hdx/freshness/database/__init__.py
hdx/freshness/database/dbdataset.py
hdx/freshness/database/dbinfodataset.py
hdx/freshness/database/dborganization.py
hdx/freshness/database/dbresource.py
hdx/freshness/database/dbrun.py
hdx/freshness/dbactions/__init__.py
hdx/freshness/dbactions/__main__.py
hdx/freshness/dbactions/dbclean.py
hdx/freshness/dbactions/dbclone.py
hdx/freshness/emailer/app/__init__.py
hdx/freshness/emailer/app/__main__.py
hdx/freshness/emailer/app/datafreshnessstatus.py
hdx/freshness/emailer/app/project_configuration.yml
hdx/freshness/emailer/utils/__init__.py
hdx/freshness/emailer/utils/databasequeries.py
hdx/freshness/emailer/utils/freshnessemail.py
hdx/freshness/emailer/utils/hdxhelper.py
hdx/freshness/emailer/utils/sheet.py
hdx/freshness/testdata/__init__.py
hdx/freshness/testdata/dbtestdataset.py
hdx/freshness/testdata/dbtestdate.py
hdx/freshness/testdata/dbtesthashresult.py
hdx/freshness/testdata/dbtestresource.py
hdx/freshness/testdata/dbtestresult.py
hdx/freshness/testdata/serialize.py
hdx/freshness/utils/__init__.py
hdx/freshness/utils/ratelimiter.py
hdx/freshness/utils/retrieval.py
hdx/freshness/utils/retry.py
hdx_data_freshness-2.0.0.dist-info/LICENSE
hdx_data_freshness-2.0.0.dist-info/METADATA
hdx_data_freshness-2.0.0.dist-info/WHEEL
hdx_data_freshness-2.0.0.dist-info/top_level.txt
hdx_data_freshness-2.0.0.dist-info/zip-safe
hdx_data_freshness-2.0.0.dist-info/RECORD
