Metadata-Version: 2.1
Name: hdx-data-freshness
Version: 2.0.0
Summary: HDX Data Freshness analyses freshness of data on HDX
Home-page: https://github.com/OCHA-DAP/hdx-data-freshness
Author: Michael Rans
Author-email: rans@email.com
License: MIT
Keywords: HDX,fresh,freshness,data freshness
Platform: any
Classifier: Development Status :: 5 - Production/Stable
Classifier: Topic :: Software Development :: Libraries :: Python Modules
Classifier: Programming Language :: Python
Classifier: Programming Language :: Python :: 3
Classifier: Programming Language :: Python :: 3 :: Only
Classifier: Programming Language :: Python :: 3.8
Classifier: Programming Language :: Python :: 3.9
Classifier: Programming Language :: Python :: 3.10
Classifier: Programming Language :: Python :: 3.11
Classifier: Programming Language :: Python :: 3.12
Classifier: Intended Audience :: Developers
Classifier: License :: OSI Approved :: MIT License
Classifier: Natural Language :: English
Classifier: Operating System :: POSIX :: Linux
Classifier: Operating System :: Unix
Classifier: Operating System :: MacOS
Classifier: Operating System :: Microsoft :: Windows
Requires-Python: >=3.8
License-File: LICENSE
Requires-Dist: aiodns
Requires-Dist: aiohttp
Requires-Dist: gspread
Requires-Dist: hdx-python-api (>=6.0.0)
Requires-Dist: hdx-python-database[postgresql] (>=1.2.3)
Requires-Dist: tqdm
Requires-Dist: uvloop
